ariadne_utils/__init__.py
ariadne_utils/cli/__init__.py
ariadne_utils/cli/utils.py
ariadne_utils/directives/__init__.py
ariadne_utils/directives/utils/__init__.py
ariadne_utils/directives/utils/rate_limit.py
ariadne_utils/django/__init__.py
ariadne_utils/exceptions.py
ariadne_utils/scalars/__init__.py
ariadne_utils/typedefs.py
ariadne_utils/utils.py
data/schema.graphql
ariadne_utils-0.1.3.dist-info/entry_points.txt
ariadne_utils-0.1.3.dist-info/WHEEL
ariadne_utils-0.1.3.dist-info/METADATA
ariadne_utils-0.1.3.dist-info/RECORD
