Metadata-Version: 2.1
Name: ariadne-utils
Version: 0.1.3
Summary: 
Home-page: https://github.com/mfdeux/ariadne-utils
License: MIT
Author: Marc Ford
Author-email: mrfxyz567@gmail.com
Requires-Python: >=3.6,<4
Classifier: License :: OSI Approved :: MIT License
Classifier: Programming Language :: Python :: 3
Classifier: Programming Language :: Python :: 3.6
Classifier: Programming Language :: Python :: 3.7
Classifier: Programming Language :: Python :: 3.8
Provides-Extra: django
Requires-Dist: ariadne (>=0.11.0)
Requires-Dist: channels (>=2.4,<3.0); extra == "django"
Requires-Dist: click (>=7.1)
Requires-Dist: django (>=2.2,<3.0); extra == "django"
Requires-Dist: python-dateutil (>=2.8)
Requires-Dist: pytimeparse (>=1.1)
Requires-Dist: validator-collection (>=1.4)
Project-URL: Repository, https://github.com/mfdeux/ariadne-utils
